LICENSE
MANIFEST.in
NOTICE
README.rst
setup.py
pyhn/__init__.py
pyhn/cachemanager.py
pyhn/config.py
pyhn/gui.py
pyhn/hnapi.py
pyhn/poller.py
pyhn/popup.py
pyhn.egg-info/PKG-INFO
pyhn.egg-info/SOURCES.txt
pyhn.egg-info/dependency_links.txt
pyhn.egg-info/requires.txt
pyhn.egg-info/top_level.txt
scripts/pyhn