Metadata-Version: 1.1
Name: pyhn
Version: 0.3.10
Summary: Hacker News in your terminal
Home-page: https://github.com/toxinu/pyhn/
Author: toxinu
Author-email: toxinu@gmail.com
License: The MIT License (MIT)
